LICENSE
MANIFEST.in
README.rst
setup.py
careful_forms/__init__.py
careful_forms/conf.py
careful_forms/forms.py
careful_forms/middleware.py
careful_forms/test_settings.py
careful_forms/test_settings_disabled.py
careful_forms/utils.py
careful_forms/tests/__init__.py
careful_forms/tests/forms.py
careful_forms/tests/models.py
careful_forms/tests/tests.py
careful_forms/tests/urls.py
careful_forms/tests/views.py
django_careful_forms.egg-info/PKG-INFO
django_careful_forms.egg-info/SOURCES.txt
django_careful_forms.egg-info/dependency_links.txt
django_careful_forms.egg-info/requires.txt
django_careful_forms.egg-info/top_level.txt