Metadata-Version: 1.0
Name: django-careful-forms
Version: 0.1
Summary: Security minded forms extension for django
Home-page: https://github.com/ulope/django-careful-forms
Author: Ulrich Petri
Author-email: mail@ulo.pe
License: MIT
Platform: UNKNOWN
Classifier: Development Status :: 3 - Alpha
Classifier: Environment :: Web Environment
Classifier: Framework :: Django
Classifier: Intended Audience :: Developers
Classifier: License :: OSI Approved :: MIT License
Classifier: Operating System :: OS Independent
Classifier: Programming Language :: Python
Classifier: Programming Language :: Python :: 2.6
Classifier: Programming Language :: Python :: 2.7
Classifier: Topic :: Software Development :: Libraries
